LICENSE
MANIFEST.in
README.rst
VERSION
requirements-dev.txt
requirements.txt
setup.cfg
setup.py
molo/__init__.py
molo.profiles.egg-info/PKG-INFO
molo.profiles.egg-info/SOURCES.txt
molo.profiles.egg-info/dependency_links.txt
molo.profiles.egg-info/namespace_packages.txt
molo.profiles.egg-info/not-zip-safe
molo.profiles.egg-info/requires.txt
molo.profiles.egg-info/top_level.txt
molo/profiles/__init__.py
molo/profiles/admin.py
molo/profiles/admin_import_export.py
molo/profiles/admin_views.py
molo/profiles/backends.py
molo/profiles/context_processors.py
molo/profiles/forms.py
molo/profiles/models.py
molo/profiles/task.py
molo/profiles/urls.py
molo/profiles/views.py
molo/profiles/wagtail_hooks.py
molo/profiles/migrations/0001_initial.py
molo/profiles/migrations/0002_add_mobile_number_field.py
molo/profiles/migrations/0003_add_email_field.py
molo/profiles/migrations/0004_add_profile_settings.py
molo/profiles/migrations/0005_add_security_questions_model.py
molo/profiles/migrations/0006_add_show_security_question_field.py
molo/profiles/migrations/0007_add_password_recovery_retries.py
molo/profiles/migrations/0008_change_num_security_questions_default.py
molo/profiles/migrations/0009_add_security_question_index_page.py
molo/profiles/migrations/0010_create_security_question_index_page.py
molo/profiles/migrations/0011_country_code.py
molo/profiles/migrations/0012_userprofilessettings_terms_and_conditions.py
molo/profiles/migrations/0013_add_location_gender_education_level_fields.py
molo/profiles/migrations/0014_add_site_to_profile.py
molo/profiles/migrations/0015_add_curent_site_to_user_profile.py
molo/profiles/migrations/0016_add_registration_token.py
molo/profiles/migrations/0017_userprofile_migrated_username.py
molo/profiles/migrations/0018_userprofile_admin_sites.py
molo/profiles/migrations/__init__.py
molo/profiles/templates/admin/frontend_users_admin_view.html
molo/profiles/templates/admin/frontend_users_date_range_filter.html
molo/profiles/templates/admin/profile_warning_message.html
molo/profiles/templates/admin/security_question_delete_warrning.html
molo/profiles/templates/profiles/base.html
molo/profiles/templates/profiles/change_password.html
molo/profiles/templates/profiles/done.html
