Metadata-Version: 1.1
Name: molo.profiles
Version: 5.4.2
Summary: User profiles to be used with Molo.
Home-page: http://github.com/praekelt/molo.profiles
Author: Praekelt Foundation
Author-email: dev@praekelt.com
License: BSD
Keywords: praekelt,mobi,web,django
Platform: UNKNOWN
Classifier: Programming Language :: Python
Classifier: Framework :: Django
Classifier: Topic :: Internet :: WWW/HTTP
Classifier: Topic :: Internet :: WWW/HTTP :: WSGI :: Application
